{"traceEvents": [{"name": "process_name", "ph": "M", "pid": 2178976, "args": {"name": "Averaged Layer Profiler"}}, {"name": "to_patch_embedding.0:forward", "ph": "X", "ts": 0, "dur": 369.59375, "pid": 2178976, "tid": 2178976}, {"name": "to_patch_embedding.1:forward", "ph": "X", "ts": 369.59375, "dur": 409.75, "pid": 2178976, "tid": 2178976}, {"name": "dropout:forward", "ph": "X", "ts": 779.34375, "dur": 98.75, "pid": 2178976, "tid": 2178976}, {"name": "transformer.layers.0.0.norm:forward", "ph": "X", "ts": 878.09375, "dur": 171.90625, "pid": 2178976, "tid": 2178976}, {"name": "transformer.layers.0.0.to_qkv:forward", "ph": "X", "ts": 1050.0, "dur": 204.0, "pid": 2178976, "tid": 2178976}, {"name": "transformer.layers.0.0.to_out.0:forward", "ph": "X", "ts": 1254.0, "dur": 209.21875, "pid": 2178976, "tid": 2178976}, {"name": "transformer.layers.0.0.to_out.1:forward", "ph": "X", "ts": 1463.21875, "dur": 63.90625, "pid": 2178976, "tid": 2178976}, {"name": "transformer.layers.0.1.net.0:forward", "ph": "X", "ts": 1527.125, "dur": 128.125, "pid": 2178976, "tid": 2178976}, {"name": "transformer.layers.0.1.net.1:forward", "ph": "X", "ts": 1655.25, "dur": 189.46875, "pid": 2178976, "tid": 2178976}, {"name": "transformer.layers.0.1.net.2:forward", "ph": "X", "ts": 1844.71875, "dur": 88.78125, "pid": 2178976, "tid": 2178976}, {"name": "transformer.layers.0.1.net.3:forward", "ph": "X", "ts": 1933.5, "dur": 59.125, "pid": 2178976, "tid": 2178976}, {"name": "transformer.layers.0.1.net.4:forward", "ph": "X", "ts": 1992.625, "dur": 161.9375, "pid": 2178976, "tid": 2178976}, {"name": "transformer.layers.0.1.net.5:forward", "ph": "X", "ts": 2154.5625, "dur": 56.625, "pid": 2178976, "tid": 2178976}, {"name": "transformer.layers.1.0.norm:forward", "ph": "X", "ts": 2211.1875, "dur": 121.5, "pid": 2178976, "tid": 2178976}, {"name": "transformer.layers.1.0.to_qkv:forward", "ph": "X", "ts": 2332.6875, "dur": 170.34375, "pid": 2178976, "tid": 2178976}, {"name": "transformer.layers.1.0.to_out.0:forward", "ph": "X", "ts": 2503.03125, "dur": 173.84375, "pid": 2178976, "tid": 2178976}, {"name": "transformer.layers.1.0.to_out.1:forward", "ph": "X", "ts": 2676.875, "dur": 59.375, "pid": 2178976, "tid": 2178976}, {"name": "transformer.layers.1.1.net.0:forward", "ph": "X", "ts": 2736.25, "dur": 112.65625, "pid": 2178976, "tid": 2178976}, {"name": "transformer.layers.1.1.net.1:forward", "ph": "X", "ts": 2848.90625, "dur": 163.75, "pid": 2178976, "tid": 2178976}, {"name": "transformer.layers.1.1.net.2:forward", "ph": "X", "ts": 3012.65625, "dur": 90.78125, "pid": 2178976, "tid": 2178976}, {"name": "transformer.layers.1.1.net.3:forward", "ph": "X", "ts": 3103.4375, "dur": 56.625, "pid": 2178976, "tid": 2178976}, {"name": "transformer.layers.1.1.net.4:forward", "ph": "X", "ts": 3160.0625, "dur": 153.3125, "pid": 2178976, "tid": 2178976}, {"name": "transformer.layers.1.1.net.5:forward", "ph": "X", "ts": 3313.375, "dur": 54.21875, "pid": 2178976, "tid": 2178976}, {"name": "transformer.layers.2.0.norm:forward", "ph": "X", "ts": 3367.59375, "dur": 119.875, "pid": 2178976, "tid": 2178976}, {"name": "transformer.layers.2.0.to_qkv:forward", "ph": "X", "ts": 3487.46875, "dur": 165.8125, "pid": 2178976, "tid": 2178976}, {"name": "transformer.layers.2.0.to_out.0:forward", "ph": "X", "ts": 3653.28125, "dur": 178.5625, "pid": 2178976, "tid": 2178976}, {"name": "transformer.layers.2.0.to_out.1:forward", "ph": "X", "ts": 3831.84375, "dur": 55.53125, "pid": 2178976, "tid": 2178976}, {"name": "transformer.layers.2.1.net.0:forward", "ph": "X", "ts": 3887.375, "dur": 112.9375, "pid": 2178976, "tid": 2178976}, {"name": "transformer.layers.2.1.net.1:forward", "ph": "X", "ts": 4000.3125, "dur": 161.625, "pid": 2178976, "tid": 2178976}, {"name": "transformer.layers.2.1.net.2:forward", "ph": "X", "ts": 4161.9375, "dur": 76.8125, "pid": 2178976, "tid": 2178976}, {"name": "transformer.layers.2.1.net.3:forward", "ph": "X", "ts": 4238.75, "dur": 56.1875, "pid": 2178976, "tid": 2178976}, {"name": "transformer.layers.2.1.net.4:forward", "ph": "X", "ts": 4294.9375, "dur": 158.1875, "pid": 2178976, "tid": 2178976}, {"name": "transformer.layers.2.1.net.5:forward", "ph": "X", "ts": 4453.125, "dur": 55.65625, "pid": 2178976, "tid": 2178976}, {"name": "transformer.layers.3.0.norm:forward", "ph": "X", "ts": 4508.78125, "dur": 122.9375, "pid": 2178976, "tid": 2178976}, {"name": "transformer.layers.3.0.to_qkv:forward", "ph": "X", "ts": 4631.71875, "dur": 160.875, "pid": 2178976, "tid": 2178976}, {"name": "transformer.layers.3.0.to_out.0:forward", "ph": "X", "ts": 4792.59375, "dur": 177.84375, "pid": 2178976, "tid": 2178976}, {"name": "transformer.layers.3.0.to_out.1:forward", "ph": "X", "ts": 4970.4375, "dur": 59.875, "pid": 2178976, "tid": 2178976}, {"name": "transformer.layers.3.1.net.0:forward", "ph": "X", "ts": 5030.3125, "dur": 106.6875, "pid": 2178976, "tid": 2178976}, {"name": "transformer.layers.3.1.net.1:forward", "ph": "X", "ts": 5137.0, "dur": 170.96875, "pid": 2178976, "tid": 2178976}, {"name": "transformer.layers.3.1.net.2:forward", "ph": "X", "ts": 5307.96875, "dur": 75.9375, "pid": 2178976, "tid": 2178976}, {"name": "transformer.layers.3.1.net.3:forward", "ph": "X", "ts": 5383.90625, "dur": 61.8125, "pid": 2178976, "tid": 2178976}, {"name": "transformer.layers.3.1.net.4:forward", "ph": "X", "ts": 5445.71875, "dur": 150.71875, "pid": 2178976, "tid": 2178976}, {"name": "transformer.layers.3.1.net.5:forward", "ph": "X", "ts": 5596.4375, "dur": 53.4375, "pid": 2178976, "tid": 2178976}, {"name": "transformer.layers.4.0.norm:forward", "ph": "X", "ts": 5649.875, "dur": 122.34375, "pid": 2178976, "tid": 2178976}, {"name": "transformer.layers.4.0.to_qkv:forward", "ph": "X", "ts": 5772.21875, "dur": 153.15625, "pid": 2178976, "tid": 2178976}, {"name": "transformer.layers.4.0.to_out.0:forward", "ph": "X", "ts": 5925.375, "dur": 168.75, "pid": 2178976, "tid": 2178976}, {"name": "transformer.layers.4.0.to_out.1:forward", "ph": "X", "ts": 6094.125, "dur": 56.4375, "pid": 2178976, "tid": 2178976}, {"name": "transformer.layers.4.1.net.0:forward", "ph": "X", "ts": 6150.5625, "dur": 113.9375, "pid": 2178976, "tid": 2178976}, {"name": "transformer.layers.4.1.net.1:forward", "ph": "X", "ts": 6264.5, "dur": 158.4375, "pid": 2178976, "tid": 2178976}, {"name": "transformer.layers.4.1.net.2:forward", "ph": "X", "ts": 6422.9375, "dur": 75.0, "pid": 2178976, "tid": 2178976}, {"name": "transformer.layers.4.1.net.3:forward", "ph": "X", "ts": 6497.9375, "dur": 51.15625, "pid": 2178976, "tid": 2178976}, {"name": "transformer.layers.4.1.net.4:forward", "ph": "X", "ts": 6549.09375, "dur": 149.375, "pid": 2178976, "tid": 2178976}, {"name": "transformer.layers.4.1.net.5:forward", "ph": "X", "ts": 6698.46875, "dur": 53.0625, "pid": 2178976, "tid": 2178976}, {"name": "transformer.layers.5.0.norm:forward", "ph": "X", "ts": 6751.53125, "dur": 109.125, "pid": 2178976, "tid": 2178976}, {"name": "transformer.layers.5.0.to_qkv:forward", "ph": "X", "ts": 6860.65625, "dur": 160.25, "pid": 2178976, "tid": 2178976}, {"name": "transformer.layers.5.0.to_out.0:forward", "ph": "X", "ts": 7020.90625, "dur": 175.4375, "pid": 2178976, "tid": 2178976}, {"name": "transformer.layers.5.0.to_out.1:forward", "ph": "X", "ts": 7196.34375, "dur": 56.15625, "pid": 2178976, "tid": 2178976}, {"name": "transformer.layers.5.1.net.0:forward", "ph": "X", "ts": 7252.5, "dur": 100.90625, "pid": 2178976, "tid": 2178976}, {"name": "transformer.layers.5.1.net.1:forward", "ph": "X", "ts": 7353.40625, "dur": 165.3125, "pid": 2178976, "tid": 2178976}, {"name": "transformer.layers.5.1.net.2:forward", "ph": "X", "ts": 7518.71875, "dur": 71.65625, "pid": 2178976, "tid": 2178976}, {"name": "transformer.layers.5.1.net.3:forward", "ph": "X", "ts": 7590.375, "dur": 628.40625, "pid": 2178976, "tid": 2178976}, {"name": "transformer.layers.5.1.net.4:forward", "ph": "X", "ts": 8218.78125, "dur": 144.4375, "pid": 2178976, "tid": 2178976}, {"name": "transformer.layers.5.1.net.5:forward", "ph": "X", "ts": 8363.21875, "dur": 52.71875, "pid": 2178976, "tid": 2178976}, {"name": "transformer.layers.6.0.norm:forward", "ph": "X", "ts": 8415.9375, "dur": 105.34375, "pid": 2178976, "tid": 2178976}, {"name": "transformer.layers.6.0.to_qkv:forward", "ph": "X", "ts": 8521.28125, "dur": 156.09375, "pid": 2178976, "tid": 2178976}, {"name": "transformer.layers.6.0.to_out.0:forward", "ph": "X", "ts": 8677.375, "dur": 177.75, "pid": 2178976, "tid": 2178976}, {"name": "transformer.layers.6.0.to_out.1:forward", "ph": "X", "ts": 8855.125, "dur": 57.1875, "pid": 2178976, "tid": 2178976}, {"name": "transformer.layers.6.1.net.0:forward", "ph": "X", "ts": 8912.3125, "dur": 101.3125, "pid": 2178976, "tid": 2178976}, {"name": "transformer.layers.6.1.net.1:forward", "ph": "X", "ts": 9013.625, "dur": 166.9375, "pid": 2178976, "tid": 2178976}, {"name": "transformer.layers.6.1.net.2:forward", "ph": "X", "ts": 9180.5625, "dur": 75.71875, "pid": 2178976, "tid": 2178976}, {"name": "transformer.layers.6.1.net.3:forward", "ph": "X", "ts": 9256.28125, "dur": 54.71875, "pid": 2178976, "tid": 2178976}, {"name": "transformer.layers.6.1.net.4:forward", "ph": "X", "ts": 9311.0, "dur": 186.34375, "pid": 2178976, "tid": 2178976}, {"name": "transformer.layers.6.1.net.5:forward", "ph": "X", "ts": 9497.34375, "dur": 53.03125, "pid": 2178976, "tid": 2178976}, {"name": "transformer.layers.7.0.norm:forward", "ph": "X", "ts": 9550.375, "dur": 107.71875, "pid": 2178976, "tid": 2178976}, {"name": "transformer.layers.7.0.to_qkv:forward", "ph": "X", "ts": 9658.09375, "dur": 143.25, "pid": 2178976, "tid": 2178976}, {"name": "transformer.layers.7.0.to_out.0:forward", "ph": "X", "ts": 9801.34375, "dur": 180.28125, "pid": 2178976, "tid": 2178976}, {"name": "transformer.layers.7.0.to_out.1:forward", "ph": "X", "ts": 9981.625, "dur": 76.6875, "pid": 2178976, "tid": 2178976}, {"name": "transformer.layers.7.1.net.0:forward", "ph": "X", "ts": 10058.3125, "dur": 114.46875, "pid": 2178976, "tid": 2178976}, {"name": "transformer.layers.7.1.net.1:forward", "ph": "X", "ts": 10172.78125, "dur": 153.75, "pid": 2178976, "tid": 2178976}, {"name": "transformer.layers.7.1.net.2:forward", "ph": "X", "ts": 10326.53125, "dur": 71.8125, "pid": 2178976, "tid": 2178976}, {"name": "transformer.layers.7.1.net.3:forward", "ph": "X", "ts": 10398.34375, "dur": 51.0, "pid": 2178976, "tid": 2178976}, {"name": "transformer.layers.7.1.net.4:forward", "ph": "X", "ts": 10449.34375, "dur": 137.625, "pid": 2178976, "tid": 2178976}, {"name": "transformer.layers.7.1.net.5:forward", "ph": "X", "ts": 10586.96875, "dur": 52.5625, "pid": 2178976, "tid": 2178976}, {"name": "transformer.layers.8.0.norm:forward", "ph": "X", "ts": 10639.53125, "dur": 106.0625, "pid": 2178976, "tid": 2178976}, {"name": "transformer.layers.8.0.to_qkv:forward", "ph": "X", "ts": 10745.59375, "dur": 142.75, "pid": 2178976, "tid": 2178976}, {"name": "transformer.layers.8.0.to_out.0:forward", "ph": "X", "ts": 10888.34375, "dur": 157.90625, "pid": 2178976, "tid": 2178976}, {"name": "transformer.layers.8.0.to_out.1:forward", "ph": "X", "ts": 11046.25, "dur": 53.5625, "pid": 2178976, "tid": 2178976}, {"name": "transformer.layers.8.1.net.0:forward", "ph": "X", "ts": 11099.8125, "dur": 101.71875, "pid": 2178976, "tid": 2178976}, {"name": "transformer.layers.8.1.net.1:forward", "ph": "X", "ts": 11201.53125, "dur": 149.75, "pid": 2178976, "tid": 2178976}, {"name": "transformer.layers.8.1.net.2:forward", "ph": "X", "ts": 11351.28125, "dur": 71.0625, "pid": 2178976, "tid": 2178976}, {"name": "transformer.layers.8.1.net.3:forward", "ph": "X", "ts": 11422.34375, "dur": 52.40625, "pid": 2178976, "tid": 2178976}, {"name": "transformer.layers.8.1.net.4:forward", "ph": "X", "ts": 11474.75, "dur": 134.96875, "pid": 2178976, "tid": 2178976}, {"name": "transformer.layers.8.1.net.5:forward", "ph": "X", "ts": 11609.71875, "dur": 52.0, "pid": 2178976, "tid": 2178976}, {"name": "transformer.layers.9.0.norm:forward", "ph": "X", "ts": 11661.71875, "dur": 103.40625, "pid": 2178976, "tid": 2178976}, {"name": "transformer.layers.9.0.to_qkv:forward", "ph": "X", "ts": 11765.125, "dur": 141.46875, "pid": 2178976, "tid": 2178976}, {"name": "transformer.layers.9.0.to_out.0:forward", "ph": "X", "ts": 11906.59375, "dur": 157.25, "pid": 2178976, "tid": 2178976}, {"name": "transformer.layers.9.0.to_out.1:forward", "ph": "X", "ts": 12063.84375, "dur": 65.9375, "pid": 2178976, "tid": 2178976}, {"name": "transformer.layers.9.1.net.0:forward", "ph": "X", "ts": 12129.78125, "dur": 99.6875, "pid": 2178976, "tid": 2178976}, {"name": "transformer.layers.9.1.net.1:forward", "ph": "X", "ts": 12229.46875, "dur": 152.0, "pid": 2178976, "tid": 2178976}, {"name": "transformer.layers.9.1.net.2:forward", "ph": "X", "ts": 12381.46875, "dur": 70.6875, "pid": 2178976, "tid": 2178976}, {"name": "transformer.layers.9.1.net.3:forward", "ph": "X", "ts": 12452.15625, "dur": 50.53125, "pid": 2178976, "tid": 2178976}, {"name": "transformer.layers.9.1.net.4:forward", "ph": "X", "ts": 12502.6875, "dur": 136.375, "pid": 2178976, "tid": 2178976}, {"name": "transformer.layers.9.1.net.5:forward", "ph": "X", "ts": 12639.0625, "dur": 52.15625, "pid": 2178976, "tid": 2178976}, {"name": "transformer.layers.10.0.norm:forward", "ph": "X", "ts": 12691.21875, "dur": 111.34375, "pid": 2178976, "tid": 2178976}, {"name": "transformer.layers.10.0.to_qkv:forward", "ph": "X", "ts": 12802.5625, "dur": 143.34375, "pid": 2178976, "tid": 2178976}, {"name": "transformer.layers.10.0.to_out.0:forward", "ph": "X", "ts": 12945.90625, "dur": 165.625, "pid": 2178976, "tid": 2178976}, {"name": "transformer.layers.10.0.to_out.1:forward", "ph": "X", "ts": 13111.53125, "dur": 55.5625, "pid": 2178976, "tid": 2178976}, {"name": "transformer.layers.10.1.net.0:forward", "ph": "X", "ts": 13167.09375, "dur": 98.65625, "pid": 2178976, "tid": 2178976}, {"name": "transformer.layers.10.1.net.1:forward", "ph": "X", "ts": 13265.75, "dur": 150.28125, "pid": 2178976, "tid": 2178976}, {"name": "transformer.layers.10.1.net.2:forward", "ph": "X", "ts": 13416.03125, "dur": 69.90625, "pid": 2178976, "tid": 2178976}, {"name": "transformer.layers.10.1.net.3:forward", "ph": "X", "ts": 13485.9375, "dur": 51.5625, "pid": 2178976, "tid": 2178976}, {"name": "transformer.layers.10.1.net.4:forward", "ph": "X", "ts": 13537.5, "dur": 134.75, "pid": 2178976, "tid": 2178976}, {"name": "transformer.layers.10.1.net.5:forward", "ph": "X", "ts": 13672.25, "dur": 50.59375, "pid": 2178976, "tid": 2178976}, {"name": "transformer.layers.11.0.norm:forward", "ph": "X", "ts": 13722.84375, "dur": 102.09375, "pid": 2178976, "tid": 2178976}, {"name": "transformer.layers.11.0.to_qkv:forward", "ph": "X", "ts": 13824.9375, "dur": 205.4375, "pid": 2178976, "tid": 2178976}, {"name": "transformer.layers.11.0.to_out.0:forward", "ph": "X", "ts": 14030.375, "dur": 159.25, "pid": 2178976, "tid": 2178976}, {"name": "transformer.layers.11.0.to_out.1:forward", "ph": "X", "ts": 14189.625, "dur": 58.8125, "pid": 2178976, "tid": 2178976}, {"name": "transformer.layers.11.1.net.0:forward", "ph": "X", "ts": 14248.4375, "dur": 98.84375, "pid": 2178976, "tid": 2178976}, {"name": "transformer.layers.11.1.net.1:forward", "ph": "X", "ts": 14347.28125, "dur": 151.8125, "pid": 2178976, "tid": 2178976}, {"name": "transformer.layers.11.1.net.2:forward", "ph": "X", "ts": 14499.09375, "dur": 71.65625, "pid": 2178976, "tid": 2178976}, {"name": "transformer.layers.11.1.net.3:forward", "ph": "X", "ts": 14570.75, "dur": 50.90625, "pid": 2178976, "tid": 2178976}, {"name": "transformer.layers.11.1.net.4:forward", "ph": "X", "ts": 14621.65625, "dur": 140.0, "pid": 2178976, "tid": 2178976}, {"name": "transformer.layers.11.1.net.5:forward", "ph": "X", "ts": 14761.65625, "dur": 51.71875, "pid": 2178976, "tid": 2178976}, {"name": "to_latent:forward", "ph": "X", "ts": 14813.375, "dur": 63.71875, "pid": 2178976, "tid": 2178976}, {"name": "mlp_head.0:forward", "ph": "X", "ts": 14877.09375, "dur": 204.65625, "pid": 2178976, "tid": 2178976}, {"name": "mlp_head.1:forward", "ph": "X", "ts": 15081.75, "dur": 150.0625, "pid": 2178976, "tid": 2178976}, {"name": "mlp_head.1:backward", "ph": "X", "ts": 15231.8125, "dur": 457.5625, "pid": 2178976, "tid": 2178976}, {"name": "mlp_head.0:backward", "ph": "X", "ts": 15689.375, "dur": 191.03125, "pid": 2178976, "tid": 2178976}, {"name": "to_latent:backward", "ph": "X", "ts": 15880.40625, "dur": 54.03125, "pid": 2178976, "tid": 2178976}, {"name": "transformer.layers.11.1.net.5:backward", "ph": "X", "ts": 15934.4375, "dur": 101.875, "pid": 2178976, "tid": 2178976}, {"name": "transformer.layers.11.1.net.4:backward", "ph": "X", "ts": 16036.3125, "dur": 391.53125, "pid": 2178976, "tid": 2178976}, {"name": "transformer.layers.11.1.net.3:backward", "ph": "X", "ts": 16427.84375, "dur": 52.84375, "pid": 2178976, "tid": 2178976}, {"name": "transformer.layers.11.1.net.2:backward", "ph": "X", "ts": 16480.6875, "dur": 115.125, "pid": 2178976, "tid": 2178976}, {"name": "transformer.layers.11.1.net.1:backward", "ph": "X", "ts": 16595.8125, "dur": 397.15625, "pid": 2178976, "tid": 2178976}, {"name": "transformer.layers.11.1.net.0:backward", "ph": "X", "ts": 16992.96875, "dur": 248.90625, "pid": 2178976, "tid": 2178976}, {"name": "transformer.layers.11.0.to_out.1:backward", "ph": "X", "ts": 17241.875, "dur": 102.21875, "pid": 2178976, "tid": 2178976}, {"name": "transformer.layers.11.0.to_out.0:backward", "ph": "X", "ts": 17344.09375, "dur": 378.0, "pid": 2178976, "tid": 2178976}, {"name": "transformer.layers.11.0.to_qkv:backward", "ph": "X", "ts": 17722.09375, "dur": 558.75, "pid": 2178976, "tid": 2178976}, {"name": "transformer.layers.11.0.norm:backward", "ph": "X", "ts": 18280.84375, "dur": 242.5, "pid": 2178976, "tid": 2178976}, {"name": "transformer.layers.10.1.net.5:backward", "ph": "X", "ts": 18523.34375, "dur": 98.21875, "pid": 2178976, "tid": 2178976}, {"name": "transformer.layers.10.1.net.4:backward", "ph": "X", "ts": 18621.5625, "dur": 388.875, "pid": 2178976, "tid": 2178976}, {"name": "transformer.layers.10.1.net.3:backward", "ph": "X", "ts": 19010.4375, "dur": 55.0, "pid": 2178976, "tid": 2178976}, {"name": "transformer.layers.10.1.net.2:backward", "ph": "X", "ts": 19065.4375, "dur": 113.875, "pid": 2178976, "tid": 2178976}, {"name": "transformer.layers.10.1.net.1:backward", "ph": "X", "ts": 19179.3125, "dur": 403.4375, "pid": 2178976, "tid": 2178976}, {"name": "transformer.layers.10.1.net.0:backward", "ph": "X", "ts": 19582.75, "dur": 246.03125, "pid": 2178976, "tid": 2178976}, {"name": "transformer.layers.10.0.to_out.1:backward", "ph": "X", "ts": 19828.78125, "dur": 96.96875, "pid": 2178976, "tid": 2178976}, {"name": "transformer.layers.10.0.to_out.0:backward", "ph": "X", "ts": 19925.75, "dur": 389.8125, "pid": 2178976, "tid": 2178976}, {"name": "transformer.layers.10.0.to_qkv:backward", "ph": "X", "ts": 20315.5625, "dur": 541.625, "pid": 2178976, "tid": 2178976}, {"name": "transformer.layers.10.0.norm:backward", "ph": "X", "ts": 20857.1875, "dur": 247.59375, "pid": 2178976, "tid": 2178976}, {"name": "transformer.layers.9.1.net.5:backward", "ph": "X", "ts": 21104.78125, "dur": 88.625, "pid": 2178976, "tid": 2178976}, {"name": "transformer.layers.9.1.net.4:backward", "ph": "X", "ts": 21193.40625, "dur": 374.9375, "pid": 2178976, "tid": 2178976}, {"name": "transformer.layers.9.1.net.3:backward", "ph": "X", "ts": 21568.34375, "dur": 54.125, "pid": 2178976, "tid": 2178976}, {"name": "transformer.layers.9.1.net.2:backward", "ph": "X", "ts": 21622.46875, "dur": 106.65625, "pid": 2178976, "tid": 2178976}, {"name": "transformer.layers.9.1.net.1:backward", "ph": "X", "ts": 21729.125, "dur": 395.1875, "pid": 2178976, "tid": 2178976}, {"name": "transformer.layers.9.1.net.0:backward", "ph": "X", "ts": 22124.3125, "dur": 239.875, "pid": 2178976, "tid": 2178976}, {"name": "transformer.layers.9.0.to_out.1:backward", "ph": "X", "ts": 22364.1875, "dur": 88.4375, "pid": 2178976, "tid": 2178976}, {"name": "transformer.layers.9.0.to_out.0:backward", "ph": "X", "ts": 22452.625, "dur": 368.53125, "pid": 2178976, "tid": 2178976}, {"name": "transformer.layers.9.0.to_qkv:backward", "ph": "X", "ts": 22821.15625, "dur": 502.625, "pid": 2178976, "tid": 2178976}, {"name": "transformer.layers.9.0.norm:backward", "ph": "X", "ts": 23323.78125, "dur": 240.4375, "pid": 2178976, "tid": 2178976}, {"name": "transformer.layers.8.1.net.5:backward", "ph": "X", "ts": 23564.21875, "dur": 84.21875, "pid": 2178976, "tid": 2178976}, {"name": "transformer.layers.8.1.net.4:backward", "ph": "X", "ts": 23648.4375, "dur": 348.34375, "pid": 2178976, "tid": 2178976}, {"name": "transformer.layers.8.1.net.3:backward", "ph": "X", "ts": 23996.78125, "dur": 49.875, "pid": 2178976, "tid": 2178976}, {"name": "transformer.layers.8.1.net.2:backward", "ph": "X", "ts": 24046.65625, "dur": 98.625, "pid": 2178976, "tid": 2178976}, {"name": "transformer.layers.8.1.net.1:backward", "ph": "X", "ts": 24145.28125, "dur": 366.375, "pid": 2178976, "tid": 2178976}, {"name": "transformer.layers.8.1.net.0:backward", "ph": "X", "ts": 24511.65625, "dur": 236.34375, "pid": 2178976, "tid": 2178976}, {"name": "transformer.layers.8.0.to_out.1:backward", "ph": "X", "ts": 24748.0, "dur": 84.1875, "pid": 2178976, "tid": 2178976}, {"name": "transformer.layers.8.0.to_out.0:backward", "ph": "X", "ts": 24832.1875, "dur": 323.375, "pid": 2178976, "tid": 2178976}, {"name": "transformer.layers.8.0.to_qkv:backward", "ph": "X", "ts": 25155.5625, "dur": 514.1875, "pid": 2178976, "tid": 2178976}, {"name": "transformer.layers.8.0.norm:backward", "ph": "X", "ts": 25669.75, "dur": 235.09375, "pid": 2178976, "tid": 2178976}, {"name": "transformer.layers.7.1.net.5:backward", "ph": "X", "ts": 25904.84375, "dur": 88.75, "pid": 2178976, "tid": 2178976}, {"name": "transformer.layers.7.1.net.4:backward", "ph": "X", "ts": 25993.59375, "dur": 321.90625, "pid": 2178976, "tid": 2178976}, {"name": "transformer.layers.7.1.net.3:backward", "ph": "X", "ts": 26315.5, "dur": 44.46875, "pid": 2178976, "tid": 2178976}, {"name": "transformer.layers.7.1.net.2:backward", "ph": "X", "ts": 26359.96875, "dur": 94.21875, "pid": 2178976, "tid": 2178976}, {"name": "transformer.layers.7.1.net.1:backward", "ph": "X", "ts": 26454.1875, "dur": 336.09375, "pid": 2178976, "tid": 2178976}, {"name": "transformer.layers.7.1.net.0:backward", "ph": "X", "ts": 26790.28125, "dur": 233.90625, "pid": 2178976, "tid": 2178976}, {"name": "transformer.layers.7.0.to_out.1:backward", "ph": "X", "ts": 27024.1875, "dur": 90.0625, "pid": 2178976, "tid": 2178976}, {"name": "transformer.layers.7.0.to_out.0:backward", "ph": "X", "ts": 27114.25, "dur": 295.03125, "pid": 2178976, "tid": 2178976}, {"name": "transformer.layers.7.0.to_qkv:backward", "ph": "X", "ts": 27409.28125, "dur": 539.78125, "pid": 2178976, "tid": 2178976}, {"name": "transformer.layers.7.0.norm:backward", "ph": "X", "ts": 27949.0625, "dur": 231.84375, "pid": 2178976, "tid": 2178976}, {"name": "transformer.layers.6.1.net.5:backward", "ph": "X", "ts": 28180.90625, "dur": 96.3125, "pid": 2178976, "tid": 2178976}, {"name": "transformer.layers.6.1.net.4:backward", "ph": "X", "ts": 28277.21875, "dur": 273.5625, "pid": 2178976, "tid": 2178976}, {"name": "transformer.layers.6.1.net.3:backward", "ph": "X", "ts": 28550.78125, "dur": 41.71875, "pid": 2178976, "tid": 2178976}, {"name": "transformer.layers.6.1.net.2:backward", "ph": "X", "ts": 28592.5, "dur": 83.875, "pid": 2178976, "tid": 2178976}, {"name": "transformer.layers.6.1.net.1:backward", "ph": "X", "ts": 28676.375, "dur": 275.5, "pid": 2178976, "tid": 2178976}, {"name": "transformer.layers.6.1.net.0:backward", "ph": "X", "ts": 28951.875, "dur": 222.65625, "pid": 2178976, "tid": 2178976}, {"name": "transformer.layers.6.0.to_out.1:backward", "ph": "X", "ts": 29174.53125, "dur": 103.375, "pid": 2178976, "tid": 2178976}, {"name": "transformer.layers.6.0.to_out.0:backward", "ph": "X", "ts": 29277.90625, "dur": 243.96875, "pid": 2178976, "tid": 2178976}, {"name": "transformer.layers.6.0.to_qkv:backward", "ph": "X", "ts": 29521.875, "dur": 550.71875, "pid": 2178976, "tid": 2178976}, {"name": "transformer.layers.6.0.norm:backward", "ph": "X", "ts": 30072.59375, "dur": 221.46875, "pid": 2178976, "tid": 2178976}, {"name": "transformer.layers.5.1.net.5:backward", "ph": "X", "ts": 30294.0625, "dur": 102.75, "pid": 2178976, "tid": 2178976}, {"name": "transformer.layers.5.1.net.4:backward", "ph": "X", "ts": 30396.8125, "dur": 251.40625, "pid": 2178976, "tid": 2178976}, {"name": "transformer.layers.5.1.net.3:backward", "ph": "X", "ts": 30648.21875, "dur": 34.09375, "pid": 2178976, "tid": 2178976}, {"name": "transformer.layers.5.1.net.2:backward", "ph": "X", "ts": 30682.3125, "dur": 79.96875, "pid": 2178976, "tid": 2178976}, {"name": "transformer.layers.5.1.net.1:backward", "ph": "X", "ts": 30762.28125, "dur": 265.6875, "pid": 2178976, "tid": 2178976}, {"name": "transformer.layers.5.1.net.0:backward", "ph": "X", "ts": 31027.96875, "dur": 221.71875, "pid": 2178976, "tid": 2178976}, {"name": "transformer.layers.5.0.to_out.1:backward", "ph": "X", "ts": 31249.6875, "dur": 102.96875, "pid": 2178976, "tid": 2178976}, {"name": "transformer.layers.5.0.to_out.0:backward", "ph": "X", "ts": 31352.65625, "dur": 244.5625, "pid": 2178976, "tid": 2178976}, {"name": "transformer.layers.5.0.to_qkv:backward", "ph": "X", "ts": 31597.21875, "dur": 552.90625, "pid": 2178976, "tid": 2178976}, {"name": "transformer.layers.5.0.norm:backward", "ph": "X", "ts": 32150.125, "dur": 220.09375, "pid": 2178976, "tid": 2178976}, {"name": "transformer.layers.4.1.net.5:backward", "ph": "X", "ts": 32370.21875, "dur": 99.28125, "pid": 2178976, "tid": 2178976}, {"name": "transformer.layers.4.1.net.4:backward", "ph": "X", "ts": 32469.5, "dur": 243.8125, "pid": 2178976, "tid": 2178976}, {"name": "transformer.layers.4.1.net.3:backward", "ph": "X", "ts": 32713.3125, "dur": 33.09375, "pid": 2178976, "tid": 2178976}, {"name": "transformer.layers.4.1.net.2:backward", "ph": "X", "ts": 32746.40625, "dur": 78.96875, "pid": 2178976, "tid": 2178976}, {"name": "transformer.layers.4.1.net.1:backward", "ph": "X", "ts": 32825.375, "dur": 261.46875, "pid": 2178976, "tid": 2178976}, {"name": "transformer.layers.4.1.net.0:backward", "ph": "X", "ts": 33086.84375, "dur": 224.0625, "pid": 2178976, "tid": 2178976}, {"name": "transformer.layers.4.0.to_out.1:backward", "ph": "X", "ts": 33310.90625, "dur": 106.40625, "pid": 2178976, "tid": 2178976}, {"name": "transformer.layers.4.0.to_out.0:backward", "ph": "X", "ts": 33417.3125, "dur": 234.8125, "pid": 2178976, "tid": 2178976}, {"name": "transformer.layers.4.0.to_qkv:backward", "ph": "X", "ts": 33652.125, "dur": 560.40625, "pid": 2178976, "tid": 2178976}, {"name": "transformer.layers.4.0.norm:backward", "ph": "X", "ts": 34212.53125, "dur": 221.375, "pid": 2178976, "tid": 2178976}, {"name": "transformer.layers.3.1.net.5:backward", "ph": "X", "ts": 34433.90625, "dur": 104.96875, "pid": 2178976, "tid": 2178976}, {"name": "transformer.layers.3.1.net.4:backward", "ph": "X", "ts": 34538.875, "dur": 228.65625, "pid": 2178976, "tid": 2178976}, {"name": "transformer.layers.3.1.net.3:backward", "ph": "X", "ts": 34767.53125, "dur": 30.0625, "pid": 2178976, "tid": 2178976}, {"name": "transformer.layers.3.1.net.2:backward", "ph": "X", "ts": 34797.59375, "dur": 76.8125, "pid": 2178976, "tid": 2178976}, {"name": "transformer.layers.3.1.net.1:backward", "ph": "X", "ts": 34874.40625, "dur": 251.625, "pid": 2178976, "tid": 2178976}, {"name": "transformer.layers.3.1.net.0:backward", "ph": "X", "ts": 35126.03125, "dur": 217.71875, "pid": 2178976, "tid": 2178976}, {"name": "transformer.layers.3.0.to_out.1:backward", "ph": "X", "ts": 35343.75, "dur": 104.25, "pid": 2178976, "tid": 2178976}, {"name": "transformer.layers.3.0.to_out.0:backward", "ph": "X", "ts": 35448.0, "dur": 244.09375, "pid": 2178976, "tid": 2178976}, {"name": "transformer.layers.3.0.to_qkv:backward", "ph": "X", "ts": 35692.09375, "dur": 575.15625, "pid": 2178976, "tid": 2178976}, {"name": "transformer.layers.3.0.norm:backward", "ph": "X", "ts": 36267.25, "dur": 216.6875, "pid": 2178976, "tid": 2178976}, {"name": "transformer.layers.2.1.net.5:backward", "ph": "X", "ts": 36483.9375, "dur": 110.03125, "pid": 2178976, "tid": 2178976}, {"name": "transformer.layers.2.1.net.4:backward", "ph": "X", "ts": 36593.96875, "dur": 208.0625, "pid": 2178976, "tid": 2178976}, {"name": "transformer.layers.2.1.net.3:backward", "ph": "X", "ts": 36802.03125, "dur": 26.84375, "pid": 2178976, "tid": 2178976}, {"name": "transformer.layers.2.1.net.2:backward", "ph": "X", "ts": 36828.875, "dur": 73.875, "pid": 2178976, "tid": 2178976}, {"name": "transformer.layers.2.1.net.1:backward", "ph": "X", "ts": 36902.75, "dur": 230.5, "pid": 2178976, "tid": 2178976}, {"name": "transformer.layers.2.1.net.0:backward", "ph": "X", "ts": 37133.25, "dur": 215.28125, "pid": 2178976, "tid": 2178976}, {"name": "transformer.layers.2.0.to_out.1:backward", "ph": "X", "ts": 37348.53125, "dur": 112.65625, "pid": 2178976, "tid": 2178976}, {"name": "transformer.layers.2.0.to_out.0:backward", "ph": "X", "ts": 37461.1875, "dur": 199.8125, "pid": 2178976, "tid": 2178976}, {"name": "transformer.layers.2.0.to_qkv:backward", "ph": "X", "ts": 37661.0, "dur": 581.3125, "pid": 2178976, "tid": 2178976}, {"name": "transformer.layers.2.0.norm:backward", "ph": "X", "ts": 38242.3125, "dur": 214.0625, "pid": 2178976, "tid": 2178976}, {"name": "transformer.layers.1.1.net.5:backward", "ph": "X", "ts": 38456.375, "dur": 111.25, "pid": 2178976, "tid": 2178976}, {"name": "transformer.layers.1.1.net.4:backward", "ph": "X", "ts": 38567.625, "dur": 201.6875, "pid": 2178976, "tid": 2178976}, {"name": "transformer.layers.1.1.net.3:backward", "ph": "X", "ts": 38769.3125, "dur": 25.78125, "pid": 2178976, "tid": 2178976}, {"name": "transformer.layers.1.1.net.2:backward", "ph": "X", "ts": 38795.09375, "dur": 73.96875, "pid": 2178976, "tid": 2178976}, {"name": "transformer.layers.1.1.net.1:backward", "ph": "X", "ts": 38869.0625, "dur": 227.21875, "pid": 2178976, "tid": 2178976}, {"name": "transformer.layers.1.1.net.0:backward", "ph": "X", "ts": 39096.28125, "dur": 217.90625, "pid": 2178976, "tid": 2178976}, {"name": "transformer.layers.1.0.to_out.1:backward", "ph": "X", "ts": 39314.1875, "dur": 112.625, "pid": 2178976, "tid": 2178976}, {"name": "transformer.layers.1.0.to_out.0:backward", "ph": "X", "ts": 39426.8125, "dur": 200.96875, "pid": 2178976, "tid": 2178976}, {"name": "transformer.layers.1.0.to_qkv:backward", "ph": "X", "ts": 39627.78125, "dur": 581.90625, "pid": 2178976, "tid": 2178976}, {"name": "transformer.layers.1.0.norm:backward", "ph": "X", "ts": 40209.6875, "dur": 218.71875, "pid": 2178976, "tid": 2178976}, {"name": "transformer.layers.0.1.net.5:backward", "ph": "X", "ts": 40428.40625, "dur": 108.125, "pid": 2178976, "tid": 2178976}, {"name": "transformer.layers.0.1.net.4:backward", "ph": "X", "ts": 40536.53125, "dur": 202.59375, "pid": 2178976, "tid": 2178976}, {"name": "transformer.layers.0.1.net.3:backward", "ph": "X", "ts": 40739.125, "dur": 25.78125, "pid": 2178976, "tid": 2178976}, {"name": "transformer.layers.0.1.net.2:backward", "ph": "X", "ts": 40764.90625, "dur": 73.28125, "pid": 2178976, "tid": 2178976}, {"name": "transformer.layers.0.1.net.1:backward", "ph": "X", "ts": 40838.1875, "dur": 227.78125, "pid": 2178976, "tid": 2178976}, {"name": "transformer.layers.0.1.net.0:backward", "ph": "X", "ts": 41065.96875, "dur": 215.15625, "pid": 2178976, "tid": 2178976}, {"name": "transformer.layers.0.0.to_out.1:backward", "ph": "X", "ts": 41281.125, "dur": 112.59375, "pid": 2178976, "tid": 2178976}, {"name": "transformer.layers.0.0.to_out.0:backward", "ph": "X", "ts": 41393.71875, "dur": 196.0, "pid": 2178976, "tid": 2178976}, {"name": "transformer.layers.0.0.to_qkv:backward", "ph": "X", "ts": 41589.71875, "dur": 578.0625, "pid": 2178976, "tid": 2178976}, {"name": "transformer.layers.0.0.norm:backward", "ph": "X", "ts": 42167.78125, "dur": 217.84375, "pid": 2178976, "tid": 2178976}, {"name": "dropout:backward", "ph": "X", "ts": 42385.625, "dur": 82.8125, "pid": 2178976, "tid": 2178976}, {"name": "to_patch_embedding.1:backward", "ph": "X", "ts": 42468.4375, "dur": 102.65625, "pid": 2178976, "tid": 2178976}, {"name": "to_patch_embedding.0:backward", "ph": "X", "ts": 42571.09375, "dur": 15.375, "pid": 2178976, "tid": 2178976}]}